{
  "Docking": {
    "Data": []
  },
  "MainWindow": {
    "GLOBAL": {
      "font": "Proggy Dotted",
      "fps": "120",
      "height": "720",
      "maximized": "0",
      "style": "0",
      "userScale": "2",
      "width": "1280",
      "xpos": "242",
      "ypos": "265"
    }
  },
  "Table": {
    "0xE56EC1C2,4": {
      "Column 0  Weight": "1.0000",
      "Column 1  Weight": "1.0000",
      "Column 2  Weight": "1.0000",
      "Column 3  Weight": "1.0000"
    }
  },
  "Window": {
    "###/FMSInfo": {
      "Collapsed": "0",
      "Pos": "60,60",
      "Size": "169,167"
    },
    "###/SmartDashboard/Field": {
      "Collapsed": "0",
      "Pos": "510,107",
      "Size": "700,491"
    },
    "###FMS": {
      "Collapsed": "0",
      "Pos": "5,540",
      "Size": "66,35"
    },
    "###Joysticks": {
      "Collapsed": "0",
      "Pos": "353,438",
      "Size": "104,35"
    },
    "###NetworkTables": {
      "Collapsed": "0",
      "Pos": "122,229",
      "Size": "750,185"
    },
    "###NetworkTables Info": {
      "Collapsed": "0",
      "Pos": "60,98",
      "Size": "750,145"
    },
    "###Other Devices": {
      "Collapsed": "0",
      "Pos": "1025,20",
      "Size": "250,695"
    },
    "###System Joysticks": {
      "Collapsed": "0",
      "Pos": "14,361",
      "Size": "148,35"
    },
    "###Timing": {
      "Collapsed": "0",
      "Pos": "5,150",
      "Size": "85,35"
    },
    "Debug##Default": {
      "Collapsed": "0",
      "Pos": "60,60",
      "Size": "400,400"
    },
    "Robot State": {
      "Collapsed": "0",
      "Pos": "5,20",
      "Size": "99,35"
    }
  }
}
